Metadata-Version: 2.4
Name: polars-fastembed-cuda
Version: 0.1.17
Summary: CUDA ONNX Runtime provider for polars-fastembed
Author: Louis Maddox
Author-email: Louis Maddox <louismmx@gmail.com>
License-Expression: MIT
Classifier: Development Status :: 4 - Beta
Classifier: License :: OSI Approved :: MIT License
Classifier: Programming Language :: Python :: 3
Requires-Python: >=3.10
